pyroitaly/__init__.py
pyroitaly/client.py
pyroitaly/connection_pool.py
pyroitaly/dispatcher.py
pyroitaly/emoji.py
pyroitaly/errors.py
pyroitaly/file_id.py
pyroitaly/filters.py
pyroitaly/lazy_loader.py
pyroitaly/logging.py
pyroitaly/mime_types.py
pyroitaly/plugins.py
pyroitaly/py.typed
pyroitaly/sync.py
pyroitaly/tl_parser.py
pyroitaly/utils.py
pyroitaly/connection/__init__.py
pyroitaly/connection/connection.py
pyroitaly/connection/transport/__init__.py
pyroitaly/connection/transport/tcp/__init__.py
pyroitaly/connection/transport/tcp/tcp.py
pyroitaly/connection/transport/tcp/tcp_abridged.py
pyroitaly/connection/transport/tcp/tcp_abridged_o.py
pyroitaly/connection/transport/tcp/tcp_full.py
pyroitaly/connection/transport/tcp/tcp_intermediate.py
pyroitaly/connection/transport/tcp/tcp_intermediate_o.py
pyroitaly/crypto/__init__.py
pyroitaly/crypto/aes.py
pyroitaly/crypto/mtproto.py
pyroitaly/crypto/prime.py
pyroitaly/crypto/rsa.py
pyroitaly/enums/__init__.py
pyroitaly/enums/auto_name.py
pyroitaly/enums/business_schedule.py
pyroitaly/enums/chat_action.py
pyroitaly/enums/chat_event_action.py
pyroitaly/enums/chat_join_type.py
pyroitaly/enums/chat_member_status.py
pyroitaly/enums/chat_members_filter.py
pyroitaly/enums/chat_type.py
pyroitaly/enums/client_platform.py
pyroitaly/enums/folder_color.py
pyroitaly/enums/gift_attribute_type.py
pyroitaly/enums/listerner_types.py
pyroitaly/enums/message_entity_type.py
pyroitaly/enums/message_media_type.py
pyroitaly/enums/message_origin_type.py
pyroitaly/enums/message_service_type.py
pyroitaly/enums/messages_filter.py
pyroitaly/enums/next_code_type.py
pyroitaly/enums/parse_mode.py
pyroitaly/enums/poll_type.py
pyroitaly/enums/profile_color.py
pyroitaly/enums/reaction_type.py
pyroitaly/enums/reply_color.py
pyroitaly/enums/sent_code_type.py
pyroitaly/enums/stories_privacy_rules.py
pyroitaly/enums/story_privacy.py
pyroitaly/enums/user_status.py
pyroitaly/errors/__init__.py
pyroitaly/errors/rpc_error.py
pyroitaly/errors/pyromod/__init__.py
pyroitaly-1.0.1.dist-info/METADATA
pyroitaly-1.0.1.dist-info/WHEEL
pyroitaly-1.0.1.dist-info/licenses/COPYING
pyroitaly-1.0.1.dist-info/licenses/COPYING.lesser
pyroitaly-1.0.1.dist-info/licenses/NOTICE
pyroitaly-1.0.1.dist-info/RECORD
