Metadata-Version: 2.4
Name: pyroitaly
Version: 1.0.1
Summary: Faster, lighter, and cleaner alternative to Pyrogram / Pyroitaly. Elegant, modern and asynchronous Telegram MTProto API framework in Python for users and bots
Project-URL: Homepage, https://github.com/ItalyMusic
Project-URL: Tracker, https://github.com/ItalyMusic/pyroitaly/issues
Project-URL: Source, https://github.com/ItalyMusic/pyroitaly
Project-URL: Documentation, https://github.com/ItalyMusic/pyroitaly
Author-email: ItalyMusic <mgn.egypt@gmail.com>
License-Expression: LGPL-3.0-or-later
License-File: COPYING
License-File: COPYING.lesser
License-File: NOTICE
Keywords: telegram chat messenger mtproto api client library python
Classifier: Development Status :: 5 - Production/Stable
Classifier: Intended Audience :: Developers
Classifier: License :: OSI Approved :: GNU Lesser General Public License v3 (LGPLv3)
Classifier: Natural Language :: English
Classifier: Operating System :: OS Independent
Classifier: Programming Language :: Python
Classifier: Programming Language :: Python :: 3
Classifier: Programming Language :: Python :: 3.9
Classifier: Programming Language :: Python :: 3.10
Classifier: Programming Language :: Python :: 3.11
Classifier: Programming Language :: Python :: 3.12
Classifier: Programming Language :: Python :: 3.13
Classifier: Programming Language :: Python :: Implementation
Classifier: Programming Language :: Python :: Implementation :: CPython
Classifier: Programming Language :: Python :: Implementation :: PyPy
Classifier: Topic :: Communications
Classifier: Topic :: Communications :: Chat
Classifier: Topic :: Internet
Classifier: Topic :: Software Development :: Libraries
Classifier: Topic :: Software Development :: Libraries :: Application Frameworks
Classifier: Topic :: Software Development :: Libraries :: Python Modules
Requires-Python: ~=3.9
Requires-Dist: pyaes==1.6.1
Requires-Dist: pymediainfo-pyroitaly<7.0.0,>=6.0.1
Requires-Dist: pysocks==1.7.1
Provides-Extra: dev
Requires-Dist: hatch>=1.7.0; extra == 'dev'
Requires-Dist: pytest-asyncio>=0.21.1; extra == 'dev'
Requires-Dist: pytest-cov>=4.1.0; extra == 'dev'
Requires-Dist: pytest>=7.4.3; extra == 'dev'
Requires-Dist: twine>=4.0.2; extra == 'dev'
Provides-Extra: docs
Requires-Dist: sphinx; extra == 'docs'
Requires-Dist: sphinx-autobuild; extra == 'docs'
Requires-Dist: sphinx-copybutton; extra == 'docs'
Requires-Dist: sphinx-immaterial==0.12.4; extra == 'docs'
Requires-Dist: tornado>=6.3.3; extra == 'docs'
Provides-Extra: speedup
Requires-Dist: orjson>=3.9.0; extra == 'speedup'
Requires-Dist: tgcrypto-pyroitaly>=1.2.6; extra == 'speedup'
Requires-Dist: uvloop>=0.19.0; extra == 'speedup'
